openapi_client/__init__.py
openapi_client/api_client.py
openapi_client/api_response.py
openapi_client/configuration.py
openapi_client/exceptions.py
openapi_client/rest.py
openapi_client/api/__init__.py
openapi_client/api/default_api.py
openapi_client/models/__init__.py
openapi_client/models/account_token_tuple_inner.py
openapi_client/models/action.py
openapi_client/models/action_object.py
openapi_client/models/add.py
openapi_client/models/add_object.py
openapi_client/models/address_and_metadata.py
openapi_client/models/and_object.py
openapi_client/models/applicable_inputs.py
openapi_client/models/apply_inputs_response.py
openapi_client/models/apply_inputs_response_links.py
openapi_client/models/apply_inputs_tx_envelope.py
openapi_client/models/assert_fail.py
openapi_client/models/assert_object.py
openapi_client/models/asset_id.py
openapi_client/models/assets.py
openapi_client/models/block_header.py
openapi_client/models/bound.py
openapi_client/models/can_choose.py
openapi_client/models/can_deposit.py
openapi_client/models/can_notify.py
openapi_client/models/case.py
openapi_client/models/case_merkleized_then.py
openapi_client/models/case_merkleized_then_object.py
openapi_client/models/case_object.py
openapi_client/models/case_then.py
openapi_client/models/case_then_object.py
openapi_client/models/choice_action.py
openapi_client/models/choice_action_object.py
openapi_client/models/choice_continuation_input.py
openapi_client/models/choice_id.py
openapi_client/models/choice_id_object.py
openapi_client/models/choice_input.py
openapi_client/models/choose_for.py
openapi_client/models/choose_for_object.py
openapi_client/models/close.py
openapi_client/models/close_object.py
openapi_client/models/continuation_input.py
openapi_client/models/contract.py
openapi_client/models/contract_header.py
openapi_client/models/contract_object.py
openapi_client/models/contract_source_ids.py
openapi_client/models/contract_state.py
openapi_client/models/create_contract_response.py
marlowe_runtime_sdk-1.0.0.dist-info/LICENSE.md
marlowe_runtime_sdk-1.0.0.dist-info/METADATA
marlowe_runtime_sdk-1.0.0.dist-info/WHEEL
marlowe_runtime_sdk-1.0.0.dist-info/top_level.txt
marlowe_runtime_sdk-1.0.0.dist-info/RECORD
