Metadata-Version: 2.1
Name: marlowe-runtime-sdk
Version: 1.0.0
Summary: Marlowe Runtime REST API
Home-page: 
Author: Nicolás Ludueña
Author-email: nicolas.luduena@txpipe.io
License: Apache 2.0
Keywords: Marlowe,Runtime,SDK,Cardano
License-File: LICENSE.md
Requires-Dist: urllib3 <2.1.0,>=1.25.3
Requires-Dist: python-dateutil
Requires-Dist: pydantic <2,>=1.10.5
Requires-Dist: aenum
